LICENSE
README.md
setup.py
qy_ip_parse/__init__.py
qy_ip_parse.egg-info/PKG-INFO
qy_ip_parse.egg-info/SOURCES.txt
qy_ip_parse.egg-info/dependency_links.txt
qy_ip_parse.egg-info/requires.txt
qy_ip_parse.egg-info/top_level.txt
qy_ip_parse.egg-info/zip-safe