Metadata-Version: 2.1
Name: qy-ip-parse
Version: 0.0.8
Summary: qy ip parse.
Home-page: UNKNOWN
Author: chenxiaolong
Author-email: cxiaolong6@gmail.com
License: MIT
Keywords: python qy ip parse
Platform: UNKNOWN
Classifier: License :: OSI Approved :: MIT License
Classifier: Programming Language :: Python
Classifier: Intended Audience :: Developers
Classifier: Operating System :: OS Independent
Requires-Python: >=2.7, !=3.0.*, !=3.1.*, !=3.2.*, !=3.3.*, !=3.4.*, !=3.5.*
License-File: LICENSE
